CONTRIBUTING.md
COPYING
ISSUE_TEMPLATE.md
MANIFEST.in
README.md
setup.py
django_template_utils.egg-info/PKG-INFO
django_template_utils.egg-info/SOURCES.txt
django_template_utils.egg-info/dependency_links.txt
django_template_utils.egg-info/requires.txt
django_template_utils.egg-info/top_level.txt
template_utils/__init__.py
template_utils/models.py
template_utils/tests.py
template_utils/views.py
template_utils/templatetags/__init__.py
template_utils/templatetags/templateutils_filters.py
template_utils/templatetags/templateutils_tags.py