Metadata-Version: 1.1
Name: django-template-utils
Version: 0.1.1
Summary: Just a collection of useful template tags and filters gathered in a single app.
Home-page: https://github.com/gerardo-orozco/django-template-utils
Author: Gerardo Orozco Mosqueda
Author-email: gerardo.orozco.mosqueda@gmail.com
License: BSD
Platform: UNKNOWN
Classifier: Development Status :: 4 - Beta
Classifier: Environment :: Web Environment
Classifier: Framework :: Django
Classifier: Intended Audience :: Developers
Classifier: License :: OSI Approved :: BSD License
Classifier: Operating System :: OS Independent
Classifier: Programming Language :: Python
Classifier: Topic :: Software Development
Classifier: Topic :: Software Development :: Libraries :: Python Modules
Classifier: Topic :: Utilities
